geostatslib/__init__.py
geostatslib/io.py
geostatslib-0.1.1.dist-info/METADATA
geostatslib-0.1.1.dist-info/WHEEL
geostatslib-0.1.1.dist-info/top_level.txt
geostatslib-0.1.1.dist-info/RECORD
